wwtpai/__init__.py
wwtpai/utils.py
wwtpai-0.1.1.dist-info/LICENSE
wwtpai-0.1.1.dist-info/METADATA
wwtpai-0.1.1.dist-info/WHEEL
wwtpai-0.1.1.dist-info/top_level.txt
wwtpai-0.1.1.dist-info/RECORD
