Metadata-Version: 2.1
Name: wwtpai
Version: 0.1.1
Summary: UNKNOWN
Home-page: https://github.com/jsdsg666/wwtpai
Author: Yuqi Wang
Author-email: 22S054041@stu.hit.edu.cn
License: GNU GPLv3
Keywords: wwtpai
Platform: UNKNOWN
License-File: LICENSE
Requires-Dist: pandas
Requires-Dist: openpyxl
